LICENSE
MANIFEST.in
README.rst
setup.py
docs/foo
examples/.dictfield.py.swp
examples/.intfield.py.swp
examples/dictfield.py
examples/hn.py
examples/intfield.py
examples/listfield.py
structominer/__init__.py
structominer/document.py
structominer/exc.py
structominer/fields.py
structominer/util.py
structominer.egg-info/PKG-INFO
structominer.egg-info/SOURCES.txt
structominer.egg-info/dependency_links.txt
structominer.egg-info/not-zip-safe
structominer.egg-info/requires.txt
structominer.egg-info/top_level.txt