Metadata-Version: 1.1
Name: structominer
Version: 0.2.0
Summary: Data scraping for a more civilized age
Home-page: https://github.com/aGHz/structominer
Author: Adrian Ghizaru
Author-email: adrian.ghizaru@gmail.com
License: MIT
Download-URL: https://github.com/aGHz/structominer/archive/0.2.0.tar.gz
Keywords: data,scraping,web,scraper
Platform: UNKNOWN
Classifier: Development Status :: 4 - Beta
Classifier: Intended Audience :: Developers
Classifier: License :: OSI Approved :: MIT License
Classifier: Topic :: Internet
Classifier: Topic :: Scientific/Engineering :: Information Analysis
Classifier: Topic :: Text Processing :: Filters
Classifier: Topic :: Text Processing :: Markup :: HTML
Classifier: Topic :: Text Processing :: Markup :: XML
